rubberize_lsp_override/__init__.py
rubberize_lsp_override/_version.py
rubberize_lsp_override/labextension/package.json
rubberize_lsp_override/labextension/static/509.e2f923b2c5120006f768.js
rubberize_lsp_override/labextension/static/728.459c7ec954ce77ca13ab.js
rubberize_lsp_override/labextension/static/remoteEntry.49223709bc294901dbf9.js
rubberize_lsp_override/labextension/static/style.js
rubberize_lsp_override/labextension/static/third-party-licenses.json
rubberize_lsp_override-0.1.0.data/data/share/jupyter/labextensions/rubberize-lsp-override/package.json
rubberize_lsp_override-0.1.0.data/data/share/jupyter/labextensions/rubberize-lsp-override/static/509.e2f923b2c5120006f768.js
rubberize_lsp_override-0.1.0.data/data/share/jupyter/labextensions/rubberize-lsp-override/static/728.459c7ec954ce77ca13ab.js
rubberize_lsp_override-0.1.0.data/data/share/jupyter/labextensions/rubberize-lsp-override/static/remoteEntry.49223709bc294901dbf9.js
rubberize_lsp_override-0.1.0.data/data/share/jupyter/labextensions/rubberize-lsp-override/static/style.js
rubberize_lsp_override-0.1.0.data/data/share/jupyter/labextensions/rubberize-lsp-override/static/third-party-licenses.json
rubberize_lsp_override-0.1.0.data/data/share/jupyter/labextensions/rubberize-lsp-override/install.json
rubberize_lsp_override-0.1.0.dist-info/METADATA
rubberize_lsp_override-0.1.0.dist-info/WHEEL
rubberize_lsp_override-0.1.0.dist-info/licenses/LICENSE
rubberize_lsp_override-0.1.0.dist-info/RECORD
