Metadata-Version: 2.4
Name: rubberize_lsp_override
Version: 0.1.0
Summary: A JupyterLab extension to override Rubberize magics in jupyterlab-lsp.
Project-URL: Homepage, https://github.com/chitoperalta/rubberize-lsp-override
Project-URL: Bug Tracker, https://github.com/chitoperalta/rubberize-lsp-override/issues
Project-URL: Repository, https://github.com/chitoperalta/rubberize-lsp-override.git
Author-email: Chito Peralta <chitoangeloperalta@gmail.com>
License: BSD 3-Clause License
License-File: LICENSE
Keywords: jupyter,jupyterlab,jupyterlab-extension
Classifier: Framework :: Jupyter
Classifier: Framework :: Jupyter :: JupyterLab
Classifier: Framework :: Jupyter :: JupyterLab :: 4
Classifier: Framework :: Jupyter :: JupyterLab :: Extensions
Classifier: Framework :: Jupyter :: JupyterLab :: Extensions :: Prebuilt
Classifier: License :: OSI Approved :: BSD License
Classifier: Programming Language :: Python
Classifier: Programming Language :: Python :: 3
Classifier: Programming Language :: Python :: 3.9
Classifier: Programming Language :: Python :: 3.10
Classifier: Programming Language :: Python :: 3.11
Classifier: Programming Language :: Python :: 3.12
Classifier: Programming Language :: Python :: 3.13
Requires-Python: >=3.9
